rpi_camera_colony/__init__.py
rpi_camera_colony/files.py
rpi_camera_colony/log.py
rpi_camera_colony/network_communication.py
rpi_camera_colony/readers.py
rpi_camera_colony/acquisition/__init__.py
rpi_camera_colony/acquisition/__main__.py
rpi_camera_colony/acquisition/acquisition_control.py
rpi_camera_colony/acquisition/camera.py
rpi_camera_colony/acquisition/remote_control.py
rpi_camera_colony/acquisition/streaming.py
rpi_camera_colony/calibration/__init__.py
rpi_camera_colony/calibration/__main__.py
rpi_camera_colony/config/__init__.py
rpi_camera_colony/config/config.py
rpi_camera_colony/config/spec.config
rpi_camera_colony/control/__init__.py
rpi_camera_colony/control/conductor.py
rpi_camera_colony/control/main.py
rpi_camera_colony/control/process_sandbox.py
rpi_camera_colony-0.5.0.dist-info/LICENSE
rpi_camera_colony-0.5.0.dist-info/METADATA
rpi_camera_colony-0.5.0.dist-info/WHEEL
rpi_camera_colony-0.5.0.dist-info/entry_points.txt
rpi_camera_colony-0.5.0.dist-info/top_level.txt
rpi_camera_colony-0.5.0.dist-info/RECORD
