Metadata-Version: 2.1
Name: rpi-camera-colony
Version: 0.5.0
Summary: RPi Camera Colony: Central control for video acquisition with (many) Raspberry Pi cameras
Home-page: https://github.com/larsrollik/rpi_camera_colony
Author: Lars B. Rollik
Author-email: L.B.Rollik@protonmail.com
License: BSD License
Project-URL: Issue Tracker, https://github.com/larsrollik/rpi_camera_colony/issues
Classifier: Programming Language :: Python :: 3
Classifier: Programming Language :: Python :: 3.6
Classifier: License :: OSI Approved :: BSD License
Classifier: Operating System :: OS Independent
Requires-Python: >=3.6
License-File: LICENSE
Requires-Dist: pyzmq
Requires-Dist: tornado
Requires-Dist: tqdm
Requires-Dist: configobj
Requires-Dist: numpy
Requires-Dist: pandas
Requires-Dist: rich
Provides-Extra: dev
Requires-Dist: black ; extra == 'dev'
Requires-Dist: coverage ; extra == 'dev'
Requires-Dist: pytest-cov ; extra == 'dev'
Requires-Dist: pytest ; extra == 'dev'
Requires-Dist: gitpython ; extra == 'dev'
Requires-Dist: bump2version ; extra == 'dev'
Requires-Dist: pre-commit ; extra == 'dev'
Requires-Dist: flake8 ; extra == 'dev'
Provides-Extra: rpi
Requires-Dist: picamera ; extra == 'rpi'
Requires-Dist: RPi.GPIO ; extra == 'rpi'
